pywayland.libs/libffi-3a37023a.so.6.0.2
pywayland.libs/libwayland-server-cccc50f9.so.0.23.0
pywayland.libs/libwayland-client-b9b885b1.so.0.23.0
pywayland-0.4.18.dist-info/WHEEL
pywayland-0.4.18.dist-info/entry_points.txt
pywayland-0.4.18.dist-info/LICENSE
pywayland-0.4.18.dist-info/top_level.txt
pywayland-0.4.18.dist-info/RECORD
pywayland-0.4.18.dist-info/METADATA
pywayland/utils.py
pywayland/py.typed
pywayland/ffi_build.py
pywayland/version.py
pywayland/_ffi.abi3.so
pywayland/dispatcher.py
pywayland/__init__.py
pywayland/protocol_core/globals.py
pywayland/protocol_core/argument.py
pywayland/protocol_core/resource.py
pywayland/protocol_core/proxy.py
pywayland/protocol_core/interface.py
pywayland/protocol_core/message.py
pywayland/protocol_core/__init__.py
pywayland/scanner/protocol.py
pywayland/scanner/element.py
pywayland/scanner/entry.py
pywayland/scanner/copyright.py
pywayland/scanner/event.py
pywayland/scanner/argument.py
pywayland/scanner/method.py
pywayland/scanner/description.py
pywayland/scanner/interface.py
pywayland/scanner/printer.py
pywayland/scanner/enum.py
pywayland/scanner/__main__.py
pywayland/scanner/request.py
pywayland/scanner/__init__.py
pywayland/client/eventqueue.py
pywayland/client/__init__.py
pywayland/client/display.py
pywayland/server/eventloop.py
pywayland/server/client.py
pywayland/server/listener.py
pywayland/server/__init__.py
pywayland/server/display.py
pywayland/_ffi/lib.pyi
pywayland/_ffi/ffi.pyi
pywayland/_ffi/__init__.pyi
pywayland/protocol/__init__.py
pywayland/protocol/text_input_unstable_v1/zwp_text_input_manager_v1.py
pywayland/protocol/text_input_unstable_v1/zwp_text_input_v1.py
pywayland/protocol/text_input_unstable_v1/__init__.py
pywayland/protocol/tablet_unstable_v2/zwp_tablet_pad_v2.py
pywayland/protocol/tablet_unstable_v2/zwp_tablet_v2.py
pywayland/protocol/tablet_unstable_v2/zwp_tablet_pad_group_v2.py
pywayland/protocol/tablet_unstable_v2/zwp_tablet_pad_ring_v2.py
pywayland/protocol/tablet_unstable_v2/zwp_tablet_pad_strip_v2.py
pywayland/protocol/tablet_unstable_v2/zwp_tablet_manager_v2.py
pywayland/protocol/tablet_unstable_v2/zwp_tablet_seat_v2.py
