Metadata-Version: 2.1
Name: pywayland
Version: 0.4.18
Summary: Python bindings for the libwayland library written in pure Python
Author-email: Sean Vig <sean.v.775@gmail.com>
License: Apache License 2.0
Project-URL: homepage, https://github.com/flacjacket/pywayland
Project-URL: documentation, https://pywayland.readthedocs.io
Project-URL: source, https://github.com/flacjacket/pywayland
Project-URL: issues, https://github.com/flacjacket/pywayland/issues
Classifier: Development Status :: 2 - Pre-Alpha
Classifier: License :: OSI Approved :: Apache Software License
Classifier: Operating System :: POSIX
Classifier: Operating System :: POSIX :: Linux
Classifier: Programming Language :: Python
Classifier: Programming Language :: Python :: 3.8
Classifier: Programming Language :: Python :: 3.9
Classifier: Programming Language :: Python :: 3.10
Classifier: Programming Language :: Python :: 3.11
Classifier: Programming Language :: Python :: Implementation :: CPython
Classifier: Programming Language :: Python :: Implementation :: PyPy
Classifier: Topic :: Desktop Environment :: Window Managers
Classifier: Topic :: Software Development :: Libraries
Requires-Python: >=3.8
License-File: LICENSE
Requires-Dist: cffi >=1.12.0 ; platform_python_implementation != "PyPy"
Provides-Extra: test
Requires-Dist: pytest ; extra == 'test'
